[{"id":"BFO:0000001","rdfs:label":"entity","short_label":"entity","children":["BFO:0000002","BFO:0000003"],"color":"#FFD700","depth":1,"radius":64,"fz":808.9220848497843,"fx":-486,"x":-486,"fy":-116,"y":-116,"marker":{"metadata":{"version":4.5,"type":"Object","generator":"Object3D.toJSON"},"geometries":[{"uuid":"F2E9F0A4-7111-404A-9DFC-DDC17BF22EB6","type":"SphereGeometry","radius":64,"widthSegments":6,"heightSegments":4,"phiStart":0}],"materials":[{"uuid":"20669744-3AC3-400D-9908-7B64BBFA1234","type":"MeshBasicMaterial","color":16766720,"depthFunc":3,"depthTest":true,"depthWrite":true,"stencilWrite":false,"stencilWriteMask":255,"stencilFunc":519,"stencilRef":0,"stencilFuncMask":255,"stencilFail":7680,"stencilZFail":7680,"stencilZPass":7680}],"object":{"uuid":"3FFF06F0-CCAB-4D22-9B8D-845F2C78916B","type":"Mesh","layers":1,"matrix":[1,0,0,0,0,1,0,0,0,0,1,0,0,0,0,1],"geometry":"F2E9F0A4-7111-404A-9DFC-DDC17BF22EB6","material":"20669744-3AC3-400D-9908-7B64BBFA1234"}},"__threeObj":{"metadata":{"version":4.5,"type":"Object","generator":"Object3D.toJSON"},"geometries":[{"uuid":"F2E9F0A4-7111-404A-9DFC-DDC17BF22EB6","type":"SphereGeometry","radius":64,"widthSegments":6,"heightSegments":4,"phiStart":0}],"materials":[{"uuid":"20669744-3AC3-400D-9908-7B64BBFA1234","type":"MeshBasicMaterial","color":16766720,"depthFunc":3,"depthTest":true,"depthWrite":true,"stencilWrite":false,"stencilWriteMask":255,"stencilFunc":519,"stencilRef":0,"stencilFuncMask":255,"stencilFail":7680,"stencilZFail":7680,"stencilZPass":7680}],"object":{"uuid":"9126DE49-7A8D-43CD-9D8D-610A20ABF357","type":"Group","layers":1,"matrix":[1,0,0,0,0,1,0,0,0,0,1,0,-486,-116,812,1],"children":[{"uuid":"3FFF06F0-CCAB-4D22-9B8D-845F2C78916B","type":"Mesh","layers":1,"matrix":[1,0,0,0,0,1,0,0,0,0,1,0,0,0,0,1],"geometry":"F2E9F0A4-7111-404A-9DFC-DDC17BF22EB6","material":"20669744-3AC3-400D-9908-7B64BBFA1234"}]}},"index":0,"z":812,"vx":0,"vy":0,"vz":0},{"id":"owl:Thing","label":"owl:Thing","short_label":"owl:Thing","children":[],"color":"#FFD700","depth":1,"radius":64,"fz":817.2268181018674,"fx":-1600,"x":-1600,"fy":-1600,"y":-1600,"marker":{"metadata":{"version":4.5,"type":"Object","generator":"Object3D.toJSON"},"geometries":[{"uuid":"6AF9112F-F2A9-4A1C-B41E-EE29F966E149","type":"SphereGeometry","radius":64,"widthSegments":6,"heightSegments":4,"phiStart":0}],"materials":[{"uuid":"414B96AE-719B-4430-8C1B-3618D5FBDEC3","type":"MeshBasicMaterial","color":16766720,"depthFunc":3,"depthTest":true,"depthWrite":true,"stencilWrite":false,"stencilWriteMask":255,"stencilFunc":519,"stencilRef":0,"stencilFuncMask":255,"stencilFail":7680,"stencilZFail":7680,"stencilZPass":7680}],"object":{"uuid":"217EB1CA-3F6E-4916-8D00-769BBB2D2150","type":"Mesh","layers":1,"matrix":[1,0,0,0,0,1,0,0,0,0,1,0,0,0,0,1],"geometry":"6AF9112F-F2A9-4A1C-B41E-EE29F966E149","material":"414B96AE-719B-4430-8C1B-3618D5FBDEC3"}},"__threeObj":{"metadata":{"version":4.5,"type":"Object","generator":"Object3D.toJSON"},"geometries":[{"uuid":"6AF9112F-F2A9-4A1C-B41E-EE29F966E149","type":"SphereGeometry","radius":64,"widthSegments":6,"heightSegments":4,"phiStart":0}],"materials":[{"uuid":"414B96AE-719B-4430-8C1B-3618D5FBDEC3","type":"MeshBasicMaterial","color":16766720,"depthFunc":3,"depthTest":true,"depthWrite":true,"stencilWrite":false,"stencilWriteMask":255,"stencilFunc":519,"stencilRef":0,"stencilFuncMask":255,"stencilFail":7680,"stencilZFail":7680,"stencilZPass":7680}],"object":{"uuid":"A108D5D4-C5D6-47FA-BC46-5950C0A421CA","type":"Group","layers":1,"matrix":[1,0,0,0,0,1,0,0,0,0,1,0,-1600,-1600,812,1],"children":[{"uuid":"217EB1CA-3F6E-4916-8D00-769BBB2D2150","type":"Mesh","layers":1,"matrix":[1,0,0,0,0,1,0,0,0,0,1,0,0,0,0,1],"geometry":"6AF9112F-F2A9-4A1C-B41E-EE29F966E149","material":"414B96AE-719B-4430-8C1B-3618D5FBDEC3"}]}},"index":1,"z":812,"vx":0,"vy":0,"vz":0},{"id":"BFO:0000002","rdfs:label":"continuant","short_label":"continuant","rdfs:subClassOf":["BFO:0000001"],"parent_id":"BFO:0000001","children":["BFO:0000004","BFO:0000020","BFO:0000031"],"color":"#FFD700","depth":2,"radius":32,"fz":449.75371376463863,"fx":120,"x":120,"fy":-264,"y":-264,"marker":{"metadata":{"version":4.5,"type":"Object","generator":"Object3D.toJSON"},"geometries":[{"uuid":"5BF3895F-ACDD-4477-8A27-E4CD4840359E","type":"SphereGeometry","radius":32,"widthSegments":6,"heightSegments":4,"phiStart":0}],"materials":[{"uuid":"3A95C39F-AE1C-46B5-ADE2-CC3D123CAA81","type":"MeshBasicMaterial","color":16766720,"depthFunc":3,"depthTest":true,"depthWrite":true,"stencilWrite":false,"stencilWriteMask":255,"stencilFunc":519,"stencilRef":0,"stencilFuncMask":255,"stencilFail":7680,"stencilZFail":7680,"stencilZPass":7680}],"object":{"uuid":"5DB45893-5961-4ABE-88B9-9BC9EE96EC00","type":"Mesh","layers":1,"matrix":[1,0,0,0,0,1,0,0,0,0,1,0,0,0,0,1],"geometry":"5BF3895F-ACDD-4477-8A27-E4CD4840359E","material":"3A95C39F-AE1C-46B5-ADE2-CC3D123CAA81"}},"__threeObj":{"metadata":{"version":4.5,"type":"Object","generator":"Object3D.toJSON"},"geometries":[{"uuid":"5BF3895F-ACDD-4477-8A27-E4CD4840359E","type":"SphereGeometry","radius":32,"widthSegments":6,"heightSegments":4,"phiStart":0}],"materials":[{"uuid":"3A95C39F-AE1C-46B5-ADE2-CC3D123CAA81","type":"MeshBasicMaterial","color":16766720,"depthFunc":3,"depthTest":true,"depthWrite":true,"stencilWrite":false,"stencilWriteMask":255,"stencilFunc":519,"stencilRef":0,"stencilFuncMask":255,"stencilFail":7680,"stencilZFail":7680,"stencilZPass":7680}],"object":{"uuid":"69340811-5687-4A06-809B-460FEECBDCFE","type":"Group","layers":1,"matrix":[1,0,0,0,0,1,0,0,0,0,1,0,120,-264,456,1],"children":[{"uuid":"5DB45893-5961-4ABE-88B9-9BC9EE96EC00","type":"Mesh","layers":1,"matrix":[1,0,0,0,0,1,0,0,0,0,1,0,0,0,0,1],"geometry":"5BF3895F-ACDD-4477-8A27-E4CD4840359E","material":"3A95C39F-AE1C-46B5-ADE2-CC3D123CAA81"}]}},"index":2,"z":456,"vx":0,"vy":0,"vz":0},{"id":"BFO:0000003","rdfs:label":"occurrent","short_label":"occurrent","rdfs:subClassOf":["BFO:0000001"],"parent_id":"BFO:0000001","children":["BFO:0000008","BFO:0000011","BFO:0000015","BFO:0000035"],"color":"#FFD700","depth":2,"radius":32,"fz":453.15883651084334,"fx":-1041,"x":-1041,"fy":-62,"y":-62,"marker":{"metadata":{"version":4.5,"type":"Object","generator":"Object3D.toJSON"},"geometries":[{"uuid":"877FE747-3483-4B53-BBE6-6449091EEB1E","type":"SphereGeometry","radius":32,"widthSegments":6,"heightSegments":4,"phiStart":0}],"materials":[{"uuid":"F78F5759-8C3D-4A8D-A8FD-67202A7B4B38","type":"MeshBasicMaterial","color":16766720,"depthFunc":3,"depthTest":true,"depthWrite":true,"stencilWrite":false,"stencilWriteMask":255,"stencilFunc":519,"stencilRef":0,"stencilFuncMask":255,"stencilFail":7680,"stencilZFail":7680,"stencilZPass":7680}],"object":{"uuid":"445BBEBA-E198-4FF2-B1CC-4010AA328EB7","type":"Mesh","layers":1,"matrix":[1,0,0,0,0,1,0,0,0,0,1,0,0,0,0,1],"geometry":"877FE747-3483-4B53-BBE6-6449091EEB1E","material":"F78F5759-8C3D-4A8D-A8FD-67202A7B4B38"}},"__threeObj":{"metadata":{"version":4.5,"type":"Object","generator":"Object3D.toJSON"},"geometries":[{"uuid":"877FE747-3483-4B53-BBE6-6449091EEB1E","type":"SphereGeometry","radius":32,"widthSegments":6,"heightSegments":4,"phiStart":0}],"materials":[{"uuid":"F78F5759-8C3D-4A8D-A8FD-67202A7B4B38","type":"MeshBasicMaterial","color":16766720,"depthFunc":3,"depthTest":true,"depthWrite":true,"stencilWrite":false,"stencilWriteMask":255,"stencilFunc":519,"stencilRef":0,"stencilFuncMask":255,"stencilFail":7680,"stencilZFail":7680,"stencilZPass":7680}],"object":{"uuid":"3F348820-AE86-45C0-9A7F-400D8606A28E","type":"Group","layers":1,"matrix":[1,0,0,0,0,1,0,0,0,0,1,0,-1041,-62,456,1],"children":[{"uuid":"445BBEBA-E198-4FF2-B1CC-4010AA328EB7","type":"Mesh","layers":1,"matrix":[1,0,0,0,0,1,0,0,0,0,1,0,0,0,0,1],"geometry":"877FE747-3483-4B53-BBE6-6449091EEB1E","material":"F78F5759-8C3D-4A8D-A8FD-67202A7B4B38"}]}},"index":3,"z":456,"vx":0,"vy":0,"vz":0},{"id":"BFO:0000004","rdfs:label":"independent continuant","IAO:0000115":"b is an independent continuant = Def. b is a continuant which is such that there is no c and no t such that b s-depends_on c at t. (axiom label in BFO2 Reference: [017-002])","short_label":"independent continuant","rdfs:subClassOf":["BFO:0000002"],"parent_id":"BFO:0000002","children":["BFO:0000040","BFO:0000141"],"color":"#FFD700","depth":3,"radius":16,"fz":219.02571582942304,"fx":146,"x":146,"fy":193,"y":193,"marker":{"metadata":{"version":4.5,"type":"Object","generator":"Object3D.toJSON"},"geometries":[{"uuid":"15A30812-2D79-4F33-B923-B5DC4A8641CA","type":"SphereGeometry","radius":16,"widthSegments":6,"heightSegments":4,"phiStart":0}],"materials":[{"uuid":"7E5637E2-A3D3-40DC-8638-AD7DAA0E78F4","type":"MeshBasicMaterial","color":16766720,"depthFunc":3,"depthTest":true,"depthWrite":true,"stencilWrite":false,"stencilWriteMask":255,"stencilFunc":519,"stencilRef":0,"stencilFuncMask":255,"stencilFail":7680,"stencilZFail":7680,"stencilZPass":7680}],"object":{"uuid":"D11A23E1-3D1B-408A-9603-D4805A4902A7","type":"Mesh","layers":1,"matrix":[1,0,0,0,0,1,0,0,0,0,1,0,0,0,0,1],"geometry":"15A30812-2D79-4F33-B923-B5DC4A8641CA","material":"7E5637E2-A3D3-40DC-8638-AD7DAA0E78F4"}},"__threeObj":{"metadata":{"version":4.5,"type":"Object","generator":"Object3D.toJSON"},"geometries":[{"uuid":"15A30812-2D79-4F33-B923-B5DC4A8641CA","type":"SphereGeometry","radius":16,"widthSegments":6,"heightSegments":4,"phiStart":0}],"materials":[{"uuid":"7E5637E2-A3D3-40DC-8638-AD7DAA0E78F4","type":"MeshBasicMaterial","color":16766720,"depthFunc":3,"depthTest":true,"depthWrite":true,"stencilWrite":false,"stencilWriteMask":255,"stencilFunc":519,"stencilRef":0,"stencilFuncMask":255,"stencilFail":7680,"stencilZFail":7680,"stencilZPass":7680}],"object":{"uuid":"D087AD84-6475-4B4C-AFDE-E42FA8F35CB7","type":"Group","layers":1,"matrix":[1,0,0,0,0,1,0,0,0,0,1,0,146,193,228,1],"children":[{"uuid":"D11A23E1-3D1B-408A-9603-D4805A4902A7","type":"Mesh","layers":1,"matrix":[1,0,0,0,0,1,0,0,0,0,1,0,0,0,0,1],"geometry":"15A30812-2D79-4F33-B923-B5DC4A8641CA","material":"7E5637E2-A3D3-40DC-8638-AD7DAA0E78F4"}]}},"index":4,"z":228,"vx":0,"vy":0,"vz":0},{"id":"BFO:0000020","rdfs:label":"specifically dependent continuant","IAO:0000115":"b is a specifically dependent continuant = Def. b is a continuant & there is some independent continuant c which is not a spatial region and which is such that b s-depends_on c at every time t during the course of b’s existence. (axiom label in BFO2 Reference: [050-003])","short_label":"specifically dependent ...","rdfs:subClassOf":["BFO:0000002"],"parent_id":"BFO:0000002","children":["BFO:0000017","BFO:0000019"],"color":"#FFD700","depth":3,"radius":16,"fz":233.97415591572684,"fx":96,"x":96,"fy":-747,"y":-747,"marker":{"metadata":{"version":4.5,"type":"Object","generator":"Object3D.toJSON"},"geometries":[{"uuid":"D0FC14B7-1417-4389-BC79-7D80963D5DC2","type":"SphereGeometry","radius":16,"widthSegments":6,"heightSegments":4,"phiStart":0}],"materials":[{"uuid":"55EE76D0-50F7-4E9B-9B5E-5A665C173E53","type":"MeshBasicMaterial","color":16766720,"depthFunc":3,"depthTest":true,"depthWrite":true,"stencilWrite":false,"stencilWriteMask":255,"stencilFunc":519,"stencilRef":0,"stencilFuncMask":255,"stencilFail":7680,"stencilZFail":7680,"stencilZPass":7680}],"object":{"uuid":"745B368F-BAA2-4E81-A74E-B73ABAF88CE6","type":"Mesh","layers":1,"matrix":[1,0,0,0,0,1,0,0,0,0,1,0,0,0,0,1],"geometry":"D0FC14B7-1417-4389-BC79-7D80963D5DC2","material":"55EE76D0-50F7-4E9B-9B5E-5A665C173E53"}},"__threeObj":{"metadata":{"version":4.5,"type":"Object","generator":"Object3D.toJSON"},"geometries":[{"uuid":"D0FC14B7-1417-4389-BC79-7D80963D5DC2","type":"SphereGeometry","radius":16,"widthSegments":6,"heightSegments":4,"phiStart":0}],"materials":[{"uuid":"55EE76D0-50F7-4E9B-9B5E-5A665C173E53","type":"MeshBasicMaterial","color":16766720,"depthFunc":3,"depthTest":true,"depthWrite":true,"stencilWrite":false,"stencilWriteMask":255,"stencilFunc":519,"stencilRef":0,"stencilFuncMask":255,"stencilFail":7680,"stencilZFail":7680,"stencilZPass":7680}],"object":{"uuid":"9FD83016-DB53-4FFB-8C31-E96B477E67B4","type":"Group","layers":1,"matrix":[1,0,0,0,0,1,0,0,0,0,1,0,96,-747,228,1],"children":[{"uuid":"745B368F-BAA2-4E81-A74E-B73ABAF88CE6","type":"Mesh","layers":1,"matrix":[1,0,0,0,0,1,0,0,0,0,1,0,0,0,0,1],"geometry":"D0FC14B7-1417-4389-BC79-7D80963D5DC2","material":"55EE76D0-50F7-4E9B-9B5E-5A665C173E53"}]}},"index":5,"z":228,"vx":0,"vy":0,"vz":0},{"id":"BFO:0000031","rdfs:label":"generically dependent continuant","IAO:0000115":"b is a generically dependent continuant = Def. b is a continuant that g-depends_on one or more other entities. (axiom label in BFO2 Reference: [074-001])","short_label":"generically dependent ...","rdfs:subClassOf":["BFO:0000002"],"parent_id":"BFO:0000002","children":[],"color":"#FFD700","depth":3,"radius":16,"fz":222.4268416794038,"fx":600,"x":600,"fy":-305,"y":-305,"marker":{"metadata":{"version":4.5,"type":"Object","generator":"Object3D.toJSON"},"geometries":[{"uuid":"8AA64F6D-E2FE-41FE-AE0C-A9E4F773ADE6","type":"SphereGeometry","radius":16,"widthSegments":6,"heightSegments":4,"phiStart":0}],"materials":[{"uuid":"0AC04F27-8FD4-42FB-A7B0-44E8E38B24E1","type":"MeshBasicMaterial","color":16766720,"depthFunc":3,"depthTest":true,"depthWrite":true,"stencilWrite":false,"stencilWriteMask":255,"stencilFunc":519,"stencilRef":0,"stencilFuncMask":255,"stencilFail":7680,"stencilZFail":7680,"stencilZPass":7680}],"object":{"uuid":"3683F892-9CBD-42BD-8ED8-8E087654838E","type":"Mesh","layers":1,"matrix":[1,0,0,0,0,1,0,0,0,0,1,0,0,0,0,1],"geometry":"8AA64F6D-E2FE-41FE-AE0C-A9E4F773ADE6","material":"0AC04F27-8FD4-42FB-A7B0-44E8E38B24E1"}},"__threeObj":{"metadata":{"version":4.5,"type":"Object","generator":"Object3D.toJSON"},"geometries":[{"uuid":"8AA64F6D-E2FE-41FE-AE0C-A9E4F773ADE6","type":"SphereGeometry","radius":16,"widthSegments":6,"heightSegments":4,"phiStart":0}],"materials":[{"uuid":"0AC04F27-8FD4-42FB-A7B0-44E8E38B24E1","type":"MeshBasicMaterial","color":16766720,"depthFunc":3,"depthTest":true,"depthWrite":true,"stencilWrite":false,"stencilWriteMask":255,"stencilFunc":519,"stencilRef":0,"stencilFuncMask":255,"stencilFail":7680,"stencilZFail":7680,"stencilZPass":7680}],"object":{"uuid":"B61C52C7-C203-41CF-84B7-86CACD33A8E2","type":"Group","layers":1,"matrix":[1,0,0,0,0,1,0,0,0,0,1,0,600,-305,228,1],"children":[{"uuid":"3683F892-9CBD-42BD-8ED8-8E087654838E","type":"Mesh","layers":1,"matrix":[1,0,0,0,0,1,0,0,0,0,1,0,0,0,0,1],"geometry":"8AA64F6D-E2FE-41FE-AE0C-A9E4F773ADE6","material":"0AC04F27-8FD4-42FB-A7B0-44E8E38B24E1"}]}},"index":6,"z":228,"vx":0,"vy":0,"vz":0},{"id":"BFO:0000008","rdfs:label":"temporal region","short_label":"temporal region","rdfs:subClassOf":["BFO:0000003"],"parent_id":"BFO:0000003","children":["BFO:0000038","BFO:0000148"],"color":"#FFD700","depth":3,"radius":16,"fz":237.50978768436767,"fx":-1118,"x":-1118,"fy":220,"y":220,"marker":{"metadata":{"version":4.5,"type":"Object","generator":"Object3D.toJSON"},"geometries":[{"uuid":"8F533311-6647-43D3-9727-EB2E996BA631","type":"SphereGeometry","radius":16,"widthSegments":6,"heightSegments":4,"phiStart":0}],"materials":[{"uuid":"A492D2D9-73C7-41E5-9E8C-6B73D404C0FC","type":"MeshBasicMaterial","color":16766720,"depthFunc":3,"depthTest":true,"depthWrite":true,"stencilWrite":false,"stencilWriteMask":255,"stencilFunc":519,"stencilRef":0,"stencilFuncMask":255,"stencilFail":7680,"stencilZFail":7680,"stencilZPass":7680}],"object":{"uuid":"0FE44A88-F946-4108-AC09-0556C066223E","type":"Mesh","layers":1,"matrix":[1,0,0,0,0,1,0,0,0,0,1,0,0,0,0,1],"geometry":"8F533311-6647-43D3-9727-EB2E996BA631","material":"A492D2D9-73C7-41E5-9E8C-6B73D404C0FC"}},"__threeObj":{"metadata":{"version":4.5,"type":"Object","generator":"Object3D.toJSON"},"geometries":[{"uuid":"8F533311-6647-43D3-9727-EB2E996BA631","type":"SphereGeometry","radius":16,"widthSegments":6,"heightSegments":4,"phiStart":0}],"materials":[{"uuid":"A492D2D9-73C7-41E5-9E8C-6B73D404C0FC","type":"MeshBasicMaterial","color":16766720,"depthFunc":3,"depthTest":true,"depthWrite":true,"stencilWrite":false,"stencilWriteMask":255,"stencilFunc":519,"stencilRef":0,"stencilFuncMask":255,"stencilFail":7680,"stencilZFail":7680,"stencilZPass":7680}],"object":{"uuid":"CF1BC14A-D60C-4B3F-A30D-A1A7D2ED5A71","type":"Group","layers":1,"matrix":[1,0,0,0,0,1,0,0,0,0,1,0,-1118,220,228,1],"children":[{"uuid":"0FE44A88-F946-4108-AC09-0556C066223E","type":"Mesh","layers":1,"matrix":[1,0,0,0,0,1,0,0,0,0,1,0,0,0,0,1],"geometry":"8F533311-6647-43D3-9727-EB2E996BA631","material":"A492D2D9-73C7-41E5-9E8C-6B73D404C0FC"}]}},"index":7,"z":228,"vx":0,"vy":0,"vz":0},{"id":"BFO:0000011","rdfs:label":"spatiotemporal region","short_label":"spatiotemporal region","rdfs:subClassOf":["BFO:0000003"],"parent_id":"BFO:0000003","children":[],"color":"#FFD700","depth":3,"radius":16,"fz":224.44991773759165,"fx":-817,"x":-817,"fy":-100,"y":-100,"marker":{"metadata":{"version":4.5,"type":"Object","generator":"Object3D.toJSON"},"geometries":[{"uuid":"7801D7AC-33D1-4E98-938A-8A3D27D96131","type":"SphereGeometry","radius":16,"widthSegments":6,"heightSegments":4,"phiStart":0}],"materials":[{"uuid":"03458652-9B29-4DF5-B1CF-9A7FFF2B5E8A","type":"MeshBasicMaterial","color":16766720,"depthFunc":3,"depthTest":true,"depthWrite":true,"stencilWrite":false,"stencilWriteMask":255,"stencilFunc":519,"stencilRef":0,"stencilFuncMask":255,"stencilFail":7680,"stencilZFail":7680,"stencilZPass":7680}],"object":{"uuid":"02BF5D74-5DB6-4C16-AC1A-58B0FAAEE6DB","type":"Mesh","layers":1,"matrix":[1,0,0,0,0,1,0,0,0,0,1,0,0,0,0,1],"geometry":"7801D7AC-33D1-4E98-938A-8A3D27D96131","material":"03458652-9B29-4DF5-B1CF-9A7FFF2B5E8A"}},"__threeObj":{"metadata":{"version":4.5,"type":"Object","generator":"Object3D.toJSON"},"geometries":[{"uuid":"7801D7AC-33D1-4E98-938A-8A3D27D96131","type":"SphereGeometry","radius":16,"widthSegments":6,"heightSegments":4,"phiStart":0}],"materials":[{"uuid":"03458652-9B29-4DF5-B1CF-9A7FFF2B5E8A","type":"MeshBasicMaterial","color":16766720,"depthFunc":3,"depthTest":true,"depthWrite":true,"stencilWrite":false,"stencilWriteMask":255,"stencilFunc":519,"stencilRef":0,"stencilFuncMask":255,"stencilFail":7680,"stencilZFail":7680,"stencilZPass":7680}],"object":{"uuid":"0303DA42-1910-4112-9B1F-B4BE053638AE","type":"Group","layers":1,"matrix":[1,0,0,0,0,1,0,0,0,0,1,0,-817,-100,228,1],"children":[{"uuid":"02BF5D74-5DB6-4C16-AC1A-58B0FAAEE6DB","type":"Mesh","layers":1,"matrix":[1,0,0,0,0,1,0,0,0,0,1,0,0,0,0,1],"geometry":"7801D7AC-33D1-4E98-938A-8A3D27D96131","material":"03458652-9B29-4DF5-B1CF-9A7FFF2B5E8A"}]}},"index":8,"z":228,"vx":0,"vy":0,"vz":0},{"id":"BFO:0000015","rdfs:label":"process","IAO:0000115":"p is a process = Def. p is an occurrent that has temporal proper parts and for some time t, p s-depends_on some material entity at t. (axiom label in BFO2 Reference: [083-003])","short_label":"process","rdfs:subClassOf":["BFO:0000003"],"parent_id":"BFO:0000003","children":["BFO:0000144","BFO:0000182"],"color":"#FFD700","depth":3,"radius":16,"fz":230.97948849467028,"fx":-1353,"x":-1353,"fy":-89,"y":-89,"marker":{"metadata":{"version":4.5,"type":"Object","generator":"Object3D.toJSON"},"geometries":[{"uuid":"47454E13-DB43-4D90-AF6D-58745B92A4CA","type":"SphereGeometry","radius":16,"widthSegments":6,"heightSegments":4,"phiStart":0}],"materials":[{"uuid":"0EFAF10D-C2BA-4E11-9C64-2712AA551ED6","type":"MeshBasicMaterial","color":16766720,"depthFunc":3,"depthTest":true,"depthWrite":true,"stencilWrite":false,"stencilWriteMask":255,"stencilFunc":519,"stencilRef":0,"stencilFuncMask":255,"stencilFail":7680,"stencilZFail":7680,"stencilZPass":7680}],"object":{"uuid":"D81EACA8-6CF0-4748-B351-AB7AFA5952CF","type":"Mesh","layers":1,"matrix":[1,0,0,0,0,1,0,0,0,0,1,0,0,0,0,1],"geometry":"47454E13-DB43-4D90-AF6D-58745B92A4CA","material":"0EFAF10D-C2BA-4E11-9C64-2712AA551ED6"}},"__threeObj":{"metadata":{"version":4.5,"type":"Object","generator":"Object3D.toJSON"},"geometries":[{"uuid":"47454E13-DB43-4D90-AF6D-58745B92A4CA","type":"SphereGeometry","radius":16,"widthSegments":6,"heightSegments":4,"phiStart":0}],"materials":[{"uuid":"0EFAF10D-C2BA-4E11-9C64-2712AA551ED6","type":"MeshBasicMaterial","color":16766720,"depthFunc":3,"depthTest":true,"depthWrite":true,"stencilWrite":false,"stencilWriteMask":255,"stencilFunc":519,"stencilRef":0,"stencilFuncMask":255,"stencilFail":7680,"stencilZFail":7680,"stencilZPass":7680}],"object":{"uuid":"2242BA5C-2092-4147-8BB9-4ADDEE49C36D","type":"Group","layers":1,"matrix":[1,0,0,0,0,1,0,0,0,0,1,0,-1353,-89,228,1],"children":[{"uuid":"D81EACA8-6CF0-4748-B351-AB7AFA5952CF","type":"Mesh","layers":1,"matrix":[1,0,0,0,0,1,0,0,0,0,1,0,0,0,0,1],"geometry":"47454E13-DB43-4D90-AF6D-58745B92A4CA","material":"0EFAF10D-C2BA-4E11-9C64-2712AA551ED6"}]}},"index":9,"z":228,"vx":0,"vy":0,"vz":0},{"id":"BFO:0000035","rdfs:label":"process boundary","IAO:0000115":"p is a process boundary =Def. p is a temporal part of a process & p has no proper temporal parts. (axiom label in BFO2 Reference: [084-001])","short_label":"process boundary","rdfs:subClassOf":["BFO:0000003"],"parent_id":"BFO:0000003","children":[],"color":"#FFD700","depth":3,"radius":16,"fz":226.2864203931485,"fx":-1118,"x":-1118,"fy":-510,"y":-510,"marker":{"metadata":{"version":4.5,"type":"Object","generator":"Object3D.toJSON"},"geometries":[{"uuid":"E97B427E-DD0E-4AB0-A465-5C5CA8B7EC38","type":"SphereGeometry","radius":16,"widthSegments":6,"heightSegments":4,"phiStart":0}],"materials":[{"uuid":"C92E42B0-094F-407A-BFCD-46CA92C95879","type":"MeshBasicMaterial","color":16766720,"depthFunc":3,"depthTest":true,"depthWrite":true,"stencilWrite":false,"stencilWriteMask":255,"stencilFunc":519,"stencilRef":0,"stencilFuncMask":255,"stencilFail":7680,"stencilZFail":7680,"stencilZPass":7680}],"object":{"uuid":"96DDB478-1067-4089-996D-235DBD0EB78A","type":"Mesh","layers":1,"matrix":[1,0,0,0,0,1,0,0,0,0,1,0,0,0,0,1],"geometry":"E97B427E-DD0E-4AB0-A465-5C5CA8B7EC38","material":"C92E42B0-094F-407A-BFCD-46CA92C95879"}},"__threeObj":{"metadata":{"version":4.5,"type":"Object","generator":"Object3D.toJSON"},"geometries":[{"uuid":"E97B427E-DD0E-4AB0-A465-5C5CA8B7EC38","type":"SphereGeometry","radius":16,"widthSegments":6,"heightSegments":4,"phiStart":0}],"materials":[{"uuid":"C92E42B0-094F-407A-BFCD-46CA92C95879","type":"MeshBasicMaterial","color":16766720,"depthFunc":3,"depthTest":true,"depthWrite":true,"stencilWrite":false,"stencilWriteMask":255,"stencilFunc":519,"stencilRef":0,"stencilFuncMask":255,"stencilFail":7680,"stencilZFail":7680,"stencilZPass":7680}],"object":{"uuid":"0EFF4D5F-0D9C-46F2-8D99-E72BF03E66A1","type":"Group","layers":1,"matrix":[1,0,0,0,0,1,0,0,0,0,1,0,-1118,-510,228,1],"children":[{"uuid":"96DDB478-1067-4089-996D-235DBD0EB78A","type":"Mesh","layers":1,"matrix":[1,0,0,0,0,1,0,0,0,0,1,0,0,0,0,1],"geometry":"E97B427E-DD0E-4AB0-A465-5C5CA8B7EC38","material":"C92E42B0-094F-407A-BFCD-46CA92C95879"}]}},"index":10,"z":228,"vx":0,"vy":0,"vz":0},{"id":"BFO:0000040","rdfs:label":"material entity","short_label":"material entity","rdfs:subClassOf":["BFO:0000004"],"parent_id":"BFO:0000004","children":["BFO:0000024","BFO:0000027","BFO:0000030"],"color":"#FFD700","depth":4,"radius":8,"fz":67.01819185324887,"fx":-3,"x":-3,"fy":475,"y":475,"marker":{"metadata":{"version":4.5,"type":"Object","generator":"Object3D.toJSON"},"geometries":[{"uuid":"A72A6437-1895-4FC6-8427-3B737FE13C0A","type":"SphereGeometry","radius":8,"widthSegments":6,"heightSegments":4,"phiStart":0}],"materials":[{"uuid":"D2850597-A2A2-48E1-AEB2-2261F23A3DF9","type":"MeshBasicMaterial","color":16766720,"depthFunc":3,"depthTest":true,"depthWrite":true,"stencilWrite":false,"stencilWriteMask":255,"stencilFunc":519,"stencilRef":0,"stencilFuncMask":255,"stencilFail":7680,"stencilZFail":7680,"stencilZPass":7680}],"object":{"uuid":"D55C49F3-68F2-473E-84B2-628F8DB237F6","type":"Mesh","layers":1,"matrix":[1,0,0,0,0,1,0,0,0,0,1,0,0,0,0,1],"geometry":"A72A6437-1895-4FC6-8427-3B737FE13C0A","material":"D2850597-A2A2-48E1-AEB2-2261F23A3DF9"}},"__threeObj":{"metadata":{"version":4.5,"type":"Object","generator":"Object3D.toJSON"},"geometries":[{"uuid":"A72A6437-1895-4FC6-8427-3B737FE13C0A","type":"SphereGeometry","radius":8,"widthSegments":6,"heightSegments":4,"phiStart":0}],"materials":[{"uuid":"D2850597-A2A2-48E1-AEB2-2261F23A3DF9","type":"MeshBasicMaterial","color":16766720,"depthFunc":3,"depthTest":true,"depthWrite":true,"stencilWrite":false,"stencilWriteMask":255,"stencilFunc":519,"stencilRef":0,"stencilFuncMask":255,"stencilFail":7680,"stencilZFail":7680,"stencilZPass":7680}],"object":{"uuid":"58370EE4-9231-45E7-BA40-771E07AF097D","type":"Group","layers":1,"matrix":[1,0,0,0,0,1,0,0,0,0,1,0,-3,475,64,1],"children":[{"uuid":"D55C49F3-68F2-473E-84B2-628F8DB237F6","type":"Mesh","layers":1,"matrix":[1,0,0,0,0,1,0,0,0,0,1,0,0,0,0,1],"geometry":"A72A6437-1895-4FC6-8427-3B737FE13C0A","material":"D2850597-A2A2-48E1-AEB2-2261F23A3DF9"}]}},"index":11,"z":64,"vx":0,"vy":0,"vz":0},{"id":"BFO:0000141","rdfs:label":"immaterial entity","short_label":"immaterial entity","rdfs:subClassOf":["BFO:0000004"],"parent_id":"BFO:0000004","children":["BFO:0000006","BFO:0000029","BFO:0000140"],"color":"#FFD700","depth":4,"radius":8,"fz":73.82459352772594,"fx":553,"x":553,"fy":362,"y":362,"marker":{"metadata":{"version":4.5,"type":"Object","generator":"Object3D.toJSON"},"geometries":[{"uuid":"3A70FB6D-4ECC-491A-AB6D-E8821F0A1E88","type":"SphereGeometry","radius":8,"widthSegments":6,"heightSegments":4,"phiStart":0}],"materials":[{"uuid":"9F812C5E-8389-42B1-80A9-360FDE671251","type":"MeshBasicMaterial","color":16766720,"depthFunc":3,"depthTest":true,"depthWrite":true,"stencilWrite":false,"stencilWriteMask":255,"stencilFunc":519,"stencilRef":0,"stencilFuncMask":255,"stencilFail":7680,"stencilZFail":7680,"stencilZPass":7680}],"object":{"uuid":"E5CE832C-5FA7-4CCD-9A16-32CC6A714AB4","type":"Mesh","layers":1,"matrix":[1,0,0,0,0,1,0,0,0,0,1,0,0,0,0,1],"geometry":"3A70FB6D-4ECC-491A-AB6D-E8821F0A1E88","material":"9F812C5E-8389-42B1-80A9-360FDE671251"}},"__threeObj":{"metadata":{"version":4.5,"type":"Object","generator":"Object3D.toJSON"},"geometries":[{"uuid":"3A70FB6D-4ECC-491A-AB6D-E8821F0A1E88","type":"SphereGeometry","radius":8,"widthSegments":6,"heightSegments":4,"phiStart":0}],"materials":[{"uuid":"9F812C5E-8389-42B1-80A9-360FDE671251","type":"MeshBasicMaterial","color":16766720,"depthFunc":3,"depthTest":true,"depthWrite":true,"stencilWrite":false,"stencilWriteMask":255,"stencilFunc":519,"stencilRef":0,"stencilFuncMask":255,"stencilFail":7680,"stencilZFail":7680,"stencilZPass":7680}],"object":{"uuid":"0F354378-4913-468E-AD81-2220FD456A50","type":"Group","layers":1,"matrix":[1,0,0,0,0,1,0,0,0,0,1,0,553,362,64,1],"children":[{"uuid":"E5CE832C-5FA7-4CCD-9A16-32CC6A714AB4","type":"Mesh","layers":1,"matrix":[1,0,0,0,0,1,0,0,0,0,1,0,0,0,0,1],"geometry":"3A70FB6D-4ECC-491A-AB6D-E8821F0A1E88","material":"9F812C5E-8389-42B1-80A9-360FDE671251"}]}},"index":12,"z":64,"vx":0,"vy":0,"vz":0},{"id":"BFO:0000017","rdfs:label":"realizable entity","short_label":"realizable entity","rdfs:subClassOf":["BFO:0000020"],"parent_id":"BFO:0000020","children":["BFO:0000016","BFO:0000023"],"color":"#FFD700","depth":4,"radius":8,"fz":59.29005789042956,"fx":135,"x":135,"fy":-1156,"y":-1156,"marker":{"metadata":{"version":4.5,"type":"Object","generator":"Object3D.toJSON"},"geometries":[{"uuid":"EAFDBDE0-33B6-4121-8578-92837C9C3D9C","type":"SphereGeometry","radius":8,"widthSegments":6,"heightSegments":4,"phiStart":0}],"materials":[{"uuid":"D2E17227-4464-4C65-B66E-6A795AEE9831","type":"MeshBasicMaterial","color":16766720,"depthFunc":3,"depthTest":true,"depthWrite":true,"stencilWrite":false,"stencilWriteMask":255,"stencilFunc":519,"stencilRef":0,"stencilFuncMask":255,"stencilFail":7680,"stencilZFail":7680,"stencilZPass":7680}],"object":{"uuid":"280F20DC-0EB1-4D6A-8DCE-E491AB68C4AE","type":"Mesh","layers":1,"matrix":[1,0,0,0,0,1,0,0,0,0,1,0,0,0,0,1],"geometry":"EAFDBDE0-33B6-4121-8578-92837C9C3D9C","material":"D2E17227-4464-4C65-B66E-6A795AEE9831"}},"__threeObj":{"metadata":{"version":4.5,"type":"Object","generator":"Object3D.toJSON"},"geometries":[{"uuid":"EAFDBDE0-33B6-4121-8578-92837C9C3D9C","type":"SphereGeometry","radius":8,"widthSegments":6,"heightSegments":4,"phiStart":0}],"materials":[{"uuid":"D2E17227-4464-4C65-B66E-6A795AEE9831","type":"MeshBasicMaterial","color":16766720,"depthFunc":3,"depthTest":true,"depthWrite":true,"stencilWrite":false,"stencilWriteMask":255,"stencilFunc":519,"stencilRef":0,"stencilFuncMask":255,"stencilFail":7680,"stencilZFail":7680,"stencilZPass":7680}],"object":{"uuid":"D56B5541-FC59-4294-B51E-BCCE01E777DB","type":"Group","layers":1,"matrix":[1,0,0,0,0,1,0,0,0,0,1,0,135,-1156,64,1],"children":[{"uuid":"280F20DC-0EB1-4D6A-8DCE-E491AB68C4AE","type":"Mesh","layers":1,"matrix":[1,0,0,0,0,1,0,0,0,0,1,0,0,0,0,1],"geometry":"EAFDBDE0-33B6-4121-8578-92837C9C3D9C","material":"D2E17227-4464-4C65-B66E-6A795AEE9831"}]}},"index":13,"z":64,"vx":0,"vy":0,"vz":0},{"id":"BFO:0000019","rdfs:label":"quality","short_label":"quality","rdfs:subClassOf":["BFO:0000020"],"parent_id":"BFO:0000020","children":["BFO:0000145"],"color":"#FFD700","depth":4,"radius":8,"fz":58.24335085726507,"fx":268,"x":268,"fy":-845,"y":-845,"marker":{"metadata":{"version":4.5,"type":"Object","generator":"Object3D.toJSON"},"geometries":[{"uuid":"0EC43C23-C2E4-44DC-9933-6933E25FF91E","type":"SphereGeometry","radius":8,"widthSegments":6,"heightSegments":4,"phiStart":0}],"materials":[{"uuid":"ED32AF54-D6B9-420C-AF6B-5C80ED788FFB","type":"MeshBasicMaterial","color":16766720,"depthFunc":3,"depthTest":true,"depthWrite":true,"stencilWrite":false,"stencilWriteMask":255,"stencilFunc":519,"stencilRef":0,"stencilFuncMask":255,"stencilFail":7680,"stencilZFail":7680,"stencilZPass":7680}],"object":{"uuid":"82836BBA-45C6-4263-A55D-FA2B836E1809","type":"Mesh","layers":1,"matrix":[1,0,0,0,0,1,0,0,0,0,1,0,0,0,0,1],"geometry":"0EC43C23-C2E4-44DC-9933-6933E25FF91E","material":"ED32AF54-D6B9-420C-AF6B-5C80ED788FFB"}},"__threeObj":{"metadata":{"version":4.5,"type":"Object","generator":"Object3D.toJSON"},"geometries":[{"uuid":"0EC43C23-C2E4-44DC-9933-6933E25FF91E","type":"SphereGeometry","radius":8,"widthSegments":6,"heightSegments":4,"phiStart":0}],"materials":[{"uuid":"ED32AF54-D6B9-420C-AF6B-5C80ED788FFB","type":"MeshBasicMaterial","color":16766720,"depthFunc":3,"depthTest":true,"depthWrite":true,"stencilWrite":false,"stencilWriteMask":255,"stencilFunc":519,"stencilRef":0,"stencilFuncMask":255,"stencilFail":7680,"stencilZFail":7680,"stencilZPass":7680}],"object":{"uuid":"DCC3C885-5B3F-45D5-93D1-37BAE3E32A9E","type":"Group","layers":1,"matrix":[1,0,0,0,0,1,0,0,0,0,1,0,268,-845,64,1],"children":[{"uuid":"82836BBA-45C6-4263-A55D-FA2B836E1809","type":"Mesh","layers":1,"matrix":[1,0,0,0,0,1,0,0,0,0,1,0,0,0,0,1],"geometry":"0EC43C23-C2E4-44DC-9933-6933E25FF91E","material":"ED32AF54-D6B9-420C-AF6B-5C80ED788FFB"}]}},"index":14,"z":64,"vx":0,"vy":0,"vz":0},{"id":"BFO:0000038","rdfs:label":"one-dimensional temporal region","short_label":"one-dimensional temporal ...","rdfs:subClassOf":["BFO:0000008"],"parent_id":"BFO:0000008","children":[],"color":"#FFD700","depth":4,"radius":8,"fz":73.7769021173954,"fx":-1298,"x":-1298,"fy":274,"y":274,"marker":{"metadata":{"version":4.5,"type":"Object","generator":"Object3D.toJSON"},"geometries":[{"uuid":"82897D2A-3255-49B5-B6EE-58A48CD44557","type":"SphereGeometry","radius":8,"widthSegments":6,"heightSegments":4,"phiStart":0}],"materials":[{"uuid":"E137D8D6-B8E3-4039-9144-5AC657035954","type":"MeshBasicMaterial","color":16766720,"depthFunc":3,"depthTest":true,"depthWrite":true,"stencilWrite":false,"stencilWriteMask":255,"stencilFunc":519,"stencilRef":0,"stencilFuncMask":255,"stencilFail":7680,"stencilZFail":7680,"stencilZPass":7680}],"object":{"uuid":"D39636F8-54B0-4086-A58A-C06C867C95A9","type":"Mesh","layers":1,"matrix":[1,0,0,0,0,1,0,0,0,0,1,0,0,0,0,1],"geometry":"82897D2A-3255-49B5-B6EE-58A48CD44557","material":"E137D8D6-B8E3-4039-9144-5AC657035954"}},"__threeObj":{"metadata":{"version":4.5,"type":"Object","generator":"Object3D.toJSON"},"geometries":[{"uuid":"82897D2A-3255-49B5-B6EE-58A48CD44557","type":"SphereGeometry","radius":8,"widthSegments":6,"heightSegments":4,"phiStart":0}],"materials":[{"uuid":"E137D8D6-B8E3-4039-9144-5AC657035954","type":"MeshBasicMaterial","color":16766720,"depthFunc":3,"depthTest":true,"depthWrite":true,"stencilWrite":false,"stencilWriteMask":255,"stencilFunc":519,"stencilRef":0,"stencilFuncMask":255,"stencilFail":7680,"stencilZFail":7680,"stencilZPass":7680}],"object":{"uuid":"5222D75F-0690-40ED-BD38-5DED0C6CA906","type":"Group","layers":1,"matrix":[1,0,0,0,0,1,0,0,0,0,1,0,-1298,274,64,1],"children":[{"uuid":"D39636F8-54B0-4086-A58A-C06C867C95A9","type":"Mesh","layers":1,"matrix":[1,0,0,0,0,1,0,0,0,0,1,0,0,0,0,1],"geometry":"82897D2A-3255-49B5-B6EE-58A48CD44557","material":"E137D8D6-B8E3-4039-9144-5AC657035954"}]}},"index":15,"z":64,"vx":0,"vy":0,"vz":0},{"id":"BFO:0000148","rdfs:label":"zero-dimensional temporal region","short_label":"zero-dimensional temporal ...","rdfs:subClassOf":["BFO:0000008"],"parent_id":"BFO:0000008","children":[],"color":"#FFD700","depth":4,"radius":8,"fz":71.52559225219876,"fx":-1006,"x":-1006,"fy":327,"y":327,"marker":{"metadata":{"version":4.5,"type":"Object","generator":"Object3D.toJSON"},"geometries":[{"uuid":"7ACBEC84-9991-4941-98AF-AA09AF61B090","type":"SphereGeometry","radius":8,"widthSegments":6,"heightSegments":4,"phiStart":0}],"materials":[{"uuid":"F3C537A2-6854-4C21-AC37-6B55474EA557","type":"MeshBasicMaterial","color":16766720,"depthFunc":3,"depthTest":true,"depthWrite":true,"stencilWrite":false,"stencilWriteMask":255,"stencilFunc":519,"stencilRef":0,"stencilFuncMask":255,"stencilFail":7680,"stencilZFail":7680,"stencilZPass":7680}],"object":{"uuid":"2987F497-A449-4312-99FC-36A85CCEBF94","type":"Mesh","layers":1,"matrix":[1,0,0,0,0,1,0,0,0,0,1,0,0,0,0,1],"geometry":"7ACBEC84-9991-4941-98AF-AA09AF61B090","material":"F3C537A2-6854-4C21-AC37-6B55474EA557"}},"__threeObj":{"metadata":{"version":4.5,"type":"Object","generator":"Object3D.toJSON"},"geometries":[{"uuid":"7ACBEC84-9991-4941-98AF-AA09AF61B090","type":"SphereGeometry","radius":8,"widthSegments":6,"heightSegments":4,"phiStart":0}],"materials":[{"uuid":"F3C537A2-6854-4C21-AC37-6B55474EA557","type":"MeshBasicMaterial","color":16766720,"depthFunc":3,"depthTest":true,"depthWrite":true,"stencilWrite":false,"stencilWriteMask":255,"stencilFunc":519,"stencilRef":0,"stencilFuncMask":255,"stencilFail":7680,"stencilZFail":7680,"stencilZPass":7680}],"object":{"uuid":"A138A2AB-6071-4EB0-95AC-B13113B3FB08","type":"Group","layers":1,"matrix":[1,0,0,0,0,1,0,0,0,0,1,0,-1006,327,64,1],"children":[{"uuid":"2987F497-A449-4312-99FC-36A85CCEBF94","type":"Mesh","layers":1,"matrix":[1,0,0,0,0,1,0,0,0,0,1,0,0,0,0,1],"geometry":"7ACBEC84-9991-4941-98AF-AA09AF61B090","material":"F3C537A2-6854-4C21-AC37-6B55474EA557"}]}},"index":16,"z":64,"vx":0,"vy":0,"vz":0},{"id":"BFO:0000144","rdfs:label":"process profile","IAO:0000115":"b is a process_profile =Def. there is some process c such that b process_profile_of c (axiom label in BFO2 Reference: [093-002])","short_label":"process profile","rdfs:subClassOf":["BFO:0000015"],"parent_id":"BFO:0000015","children":[],"color":"#FFD700","depth":4,"radius":8,"fz":64.92387578117184,"fx":-1469,"x":-1469,"fy":50,"y":50,"marker":{"metadata":{"version":4.5,"type":"Object","generator":"Object3D.toJSON"},"geometries":[{"uuid":"F651F2DB-94AE-4188-B163-91CA80476882","type":"SphereGeometry","radius":8,"widthSegments":6,"heightSegments":4,"phiStart":0}],"materials":[{"uuid":"DD124531-FA65-427D-84F8-672EF7515DAF","type":"MeshBasicMaterial","color":16766720,"depthFunc":3,"depthTest":true,"depthWrite":true,"stencilWrite":false,"stencilWriteMask":255,"stencilFunc":519,"stencilRef":0,"stencilFuncMask":255,"stencilFail":7680,"stencilZFail":7680,"stencilZPass":7680}],"object":{"uuid":"B02DB259-F8A9-4C0A-85BB-C3D0A257EB0B","type":"Mesh","layers":1,"matrix":[1,0,0,0,0,1,0,0,0,0,1,0,0,0,0,1],"geometry":"F651F2DB-94AE-4188-B163-91CA80476882","material":"DD124531-FA65-427D-84F8-672EF7515DAF"}},"__threeObj":{"metadata":{"version":4.5,"type":"Object","generator":"Object3D.toJSON"},"geometries":[{"uuid":"F651F2DB-94AE-4188-B163-91CA80476882","type":"SphereGeometry","radius":8,"widthSegments":6,"heightSegments":4,"phiStart":0}],"materials":[{"uuid":"DD124531-FA65-427D-84F8-672EF7515DAF","type":"MeshBasicMaterial","color":16766720,"depthFunc":3,"depthTest":true,"depthWrite":true,"stencilWrite":false,"stencilWriteMask":255,"stencilFunc":519,"stencilRef":0,"stencilFuncMask":255,"stencilFail":7680,"stencilZFail":7680,"stencilZPass":7680}],"object":{"uuid":"E86A461E-35F9-45D0-BA39-6239E1D3ED19","type":"Group","layers":1,"matrix":[1,0,0,0,0,1,0,0,0,0,1,0,-1469,50,64,1],"children":[{"uuid":"B02DB259-F8A9-4C0A-85BB-C3D0A257EB0B","type":"Mesh","layers":1,"matrix":[1,0,0,0,0,1,0,0,0,0,1,0,0,0,0,1],"geometry":"F651F2DB-94AE-4188-B163-91CA80476882","material":"DD124531-FA65-427D-84F8-672EF7515DAF"}]}},"index":17,"z":64,"vx":0,"vy":0,"vz":0},{"id":"BFO:0000182","rdfs:label":"history","short_label":"history","rdfs:subClassOf":["BFO:0000015"],"parent_id":"BFO:0000015","children":[],"color":"#FFD700","depth":4,"radius":8,"fz":72.59072095214765,"fx":-1445,"x":-1445,"fy":-265,"y":-265,"marker":{"metadata":{"version":4.5,"type":"Object","generator":"Object3D.toJSON"},"geometries":[{"uuid":"75A8DA91-8AC8-4326-9EC3-515873207E47","type":"SphereGeometry","radius":8,"widthSegments":6,"heightSegments":4,"phiStart":0}],"materials":[{"uuid":"41303791-E90C-46A8-B180-EB61195CDBC4","type":"MeshBasicMaterial","color":16766720,"depthFunc":3,"depthTest":true,"depthWrite":true,"stencilWrite":false,"stencilWriteMask":255,"stencilFunc":519,"stencilRef":0,"stencilFuncMask":255,"stencilFail":7680,"stencilZFail":7680,"stencilZPass":7680}],"object":{"uuid":"2FF1D432-268C-45E5-A466-90E51992BD0C","type":"Mesh","layers":1,"matrix":[1,0,0,0,0,1,0,0,0,0,1,0,0,0,0,1],"geometry":"75A8DA91-8AC8-4326-9EC3-515873207E47","material":"41303791-E90C-46A8-B180-EB61195CDBC4"}},"__threeObj":{"metadata":{"version":4.5,"type":"Object","generator":"Object3D.toJSON"},"geometries":[{"uuid":"75A8DA91-8AC8-4326-9EC3-515873207E47","type":"SphereGeometry","radius":8,"widthSegments":6,"heightSegments":4,"phiStart":0}],"materials":[{"uuid":"41303791-E90C-46A8-B180-EB61195CDBC4","type":"MeshBasicMaterial","color":16766720,"depthFunc":3,"depthTest":true,"depthWrite":true,"stencilWrite":false,"stencilWriteMask":255,"stencilFunc":519,"stencilRef":0,"stencilFuncMask":255,"stencilFail":7680,"stencilZFail":7680,"stencilZPass":7680}],"object":{"uuid":"A0EBA1BE-26FA-4916-A275-AC597AC1A4F2","type":"Group","layers":1,"matrix":[1,0,0,0,0,1,0,0,0,0,1,0,-1445,-265,64,1],"children":[{"uuid":"2FF1D432-268C-45E5-A466-90E51992BD0C","type":"Mesh","layers":1,"matrix":[1,0,0,0,0,1,0,0,0,0,1,0,0,0,0,1],"geometry":"75A8DA91-8AC8-4326-9EC3-515873207E47","material":"41303791-E90C-46A8-B180-EB61195CDBC4"}]}},"index":18,"z":64,"vx":0,"vy":0,"vz":0},{"id":"BFO:0000024","rdfs:label":"fiat object part","short_label":"fiat object part","rdfs:subClassOf":["BFO:0000040"],"parent_id":"BFO:0000040","children":[],"color":"#FFD700","depth":5,"radius":4,"fz":-75.51483803694612,"fx":164,"x":164,"fy":571,"y":571,"marker":{"metadata":{"version":4.5,"type":"Object","generator":"Object3D.toJSON"},"geometries":[{"uuid":"B53ED960-505F-48A6-9938-45ABC185DFEC","type":"SphereGeometry","radius":5,"widthSegments":6,"heightSegments":4,"phiStart":0}],"materials":[{"uuid":"7E755898-5EE5-4006-8AD0-CBFB5A4A12D0","type":"MeshBasicMaterial","color":16766720,"depthFunc":3,"depthTest":true,"depthWrite":true,"stencilWrite":false,"stencilWriteMask":255,"stencilFunc":519,"stencilRef":0,"stencilFuncMask":255,"stencilFail":7680,"stencilZFail":7680,"stencilZPass":7680}],"object":{"uuid":"C4DAA949-A467-4B4B-A0A6-5C12E7C2062A","type":"Mesh","layers":1,"matrix":[1,0,0,0,0,1,0,0,0,0,1,0,0,0,0,1],"geometry":"B53ED960-505F-48A6-9938-45ABC185DFEC","material":"7E755898-5EE5-4006-8AD0-CBFB5A4A12D0"}},"__threeObj":{"metadata":{"version":4.5,"type":"Object","generator":"Object3D.toJSON"},"geometries":[{"uuid":"B53ED960-505F-48A6-9938-45ABC185DFEC","type":"SphereGeometry","radius":5,"widthSegments":6,"heightSegments":4,"phiStart":0}],"materials":[{"uuid":"7E755898-5EE5-4006-8AD0-CBFB5A4A12D0","type":"MeshBasicMaterial","color":16766720,"depthFunc":3,"depthTest":true,"depthWrite":true,"stencilWrite":false,"stencilWriteMask":255,"stencilFunc":519,"stencilRef":0,"stencilFuncMask":255,"stencilFail":7680,"stencilZFail":7680,"stencilZPass":7680}],"object":{"uuid":"FE9588D9-E8F6-4F7E-A5CF-20558ACCFE6E","type":"Group","layers":1,"matrix":[1,0,0,0,0,1,0,0,0,0,1,0,164,571,-68,1],"children":[{"uuid":"C4DAA949-A467-4B4B-A0A6-5C12E7C2062A","type":"Mesh","layers":1,"matrix":[1,0,0,0,0,1,0,0,0,0,1,0,0,0,0,1],"geometry":"B53ED960-505F-48A6-9938-45ABC185DFEC","material":"7E755898-5EE5-4006-8AD0-CBFB5A4A12D0"}]}},"index":19,"z":-68,"vx":0,"vy":0,"vz":0},{"id":"BFO:0000027","rdfs:label":"object aggregate","short_label":"object aggregate","rdfs:subClassOf":["BFO:0000040"],"parent_id":"BFO:0000040","children":[],"color":"#FFD700","depth":5,"radius":4,"fz":-74.12201031666936,"fx":-100,"x":-100,"fy":650,"y":650,"marker":{"metadata":{"version":4.5,"type":"Object","generator":"Object3D.toJSON"},"geometries":[{"uuid":"F497394C-3B28-460E-86B6-93017D23AFB1","type":"SphereGeometry","radius":5,"widthSegments":6,"heightSegments":4,"phiStart":0}],"materials":[{"uuid":"5E15508D-1BA3-42C7-9410-F360F2F878DE","type":"MeshBasicMaterial","color":16766720,"depthFunc":3,"depthTest":true,"depthWrite":true,"stencilWrite":false,"stencilWriteMask":255,"stencilFunc":519,"stencilRef":0,"stencilFuncMask":255,"stencilFail":7680,"stencilZFail":7680,"stencilZPass":7680}],"object":{"uuid":"9986C8F3-1EF2-4A22-A0EA-6DA15089BB2B","type":"Mesh","layers":1,"matrix":[1,0,0,0,0,1,0,0,0,0,1,0,0,0,0,1],"geometry":"F497394C-3B28-460E-86B6-93017D23AFB1","material":"5E15508D-1BA3-42C7-9410-F360F2F878DE"}},"__threeObj":{"metadata":{"version":4.5,"type":"Object","generator":"Object3D.toJSON"},"geometries":[{"uuid":"F497394C-3B28-460E-86B6-93017D23AFB1","type":"SphereGeometry","radius":5,"widthSegments":6,"heightSegments":4,"phiStart":0}],"materials":[{"uuid":"5E15508D-1BA3-42C7-9410-F360F2F878DE","type":"MeshBasicMaterial","color":16766720,"depthFunc":3,"depthTest":true,"depthWrite":true,"stencilWrite":false,"stencilWriteMask":255,"stencilFunc":519,"stencilRef":0,"stencilFuncMask":255,"stencilFail":7680,"stencilZFail":7680,"stencilZPass":7680}],"object":{"uuid":"1F49187F-0451-4623-ABF9-EEEA2B15E95C","type":"Group","layers":1,"matrix":[1,0,0,0,0,1,0,0,0,0,1,0,-100,650,-68,1],"children":[{"uuid":"9986C8F3-1EF2-4A22-A0EA-6DA15089BB2B","type":"Mesh","layers":1,"matrix":[1,0,0,0,0,1,0,0,0,0,1,0,0,0,0,1],"geometry":"F497394C-3B28-460E-86B6-93017D23AFB1","material":"5E15508D-1BA3-42C7-9410-F360F2F878DE"}]}},"index":20,"z":-68,"vx":0,"vy":0,"vz":0},{"id":"BFO:0000030","rdfs:label":"object","short_label":"object","rdfs:subClassOf":["BFO:0000040"],"parent_id":"BFO:0000040","children":[],"color":"#FFD700","depth":5,"radius":4,"fz":-61.976943758742166,"fx":-302,"x":-302,"fy":450,"y":450,"marker":{"metadata":{"version":4.5,"type":"Object","generator":"Object3D.toJSON"},"geometries":[{"uuid":"A6334350-8CB7-4DB1-86C5-6042ED615605","type":"SphereGeometry","radius":5,"widthSegments":6,"heightSegments":4,"phiStart":0}],"materials":[{"uuid":"21D75BA6-3595-4A98-B5D0-B1651AF70270","type":"MeshBasicMaterial","color":16766720,"depthFunc":3,"depthTest":true,"depthWrite":true,"stencilWrite":false,"stencilWriteMask":255,"stencilFunc":519,"stencilRef":0,"stencilFuncMask":255,"stencilFail":7680,"stencilZFail":7680,"stencilZPass":7680}],"object":{"uuid":"31A8400D-B39F-4BA7-9A48-C9878951F6E5","type":"Mesh","layers":1,"matrix":[1,0,0,0,0,1,0,0,0,0,1,0,0,0,0,1],"geometry":"A6334350-8CB7-4DB1-86C5-6042ED615605","material":"21D75BA6-3595-4A98-B5D0-B1651AF70270"}},"__threeObj":{"metadata":{"version":4.5,"type":"Object","generator":"Object3D.toJSON"},"geometries":[{"uuid":"A6334350-8CB7-4DB1-86C5-6042ED615605","type":"SphereGeometry","radius":5,"widthSegments":6,"heightSegments":4,"phiStart":0}],"materials":[{"uuid":"21D75BA6-3595-4A98-B5D0-B1651AF70270","type":"MeshBasicMaterial","color":16766720,"depthFunc":3,"depthTest":true,"depthWrite":true,"stencilWrite":false,"stencilWriteMask":255,"stencilFunc":519,"stencilRef":0,"stencilFuncMask":255,"stencilFail":7680,"stencilZFail":7680,"stencilZPass":7680}],"object":{"uuid":"B4F861E6-09C3-4430-A474-AAA467317627","type":"Group","layers":1,"matrix":[1,0,0,0,0,1,0,0,0,0,1,0,-302,450,-68,1],"children":[{"uuid":"31A8400D-B39F-4BA7-9A48-C9878951F6E5","type":"Mesh","layers":1,"matrix":[1,0,0,0,0,1,0,0,0,0,1,0,0,0,0,1],"geometry":"A6334350-8CB7-4DB1-86C5-6042ED615605","material":"21D75BA6-3595-4A98-B5D0-B1651AF70270"}]}},"index":21,"z":-68,"vx":0,"vy":0,"vz":0},{"id":"BFO:0000006","rdfs:label":"spatial region","short_label":"spatial region","rdfs:subClassOf":["BFO:0000141"],"parent_id":"BFO:0000141","children":["BFO:0000009","BFO:0000018","BFO:0000026","BFO:0000028"],"color":"#FFD700","depth":5,"radius":4,"fz":-60.058059935683886,"fx":755,"x":755,"fy":724,"y":724,"marker":{"metadata":{"version":4.5,"type":"Object","generator":"Object3D.toJSON"},"geometries":[{"uuid":"FAEED661-6D77-4353-AC8A-864483404956","type":"SphereGeometry","radius":5,"widthSegments":6,"heightSegments":4,"phiStart":0}],"materials":[{"uuid":"AB5A0168-698E-49CB-B5EB-71198AEBF417","type":"MeshBasicMaterial","color":16766720,"depthFunc":3,"depthTest":true,"depthWrite":true,"stencilWrite":false,"stencilWriteMask":255,"stencilFunc":519,"stencilRef":0,"stencilFuncMask":255,"stencilFail":7680,"stencilZFail":7680,"stencilZPass":7680}],"object":{"uuid":"46FDDBAD-5415-4310-A508-FEEEA70720AD","type":"Mesh","layers":1,"matrix":[1,0,0,0,0,1,0,0,0,0,1,0,0,0,0,1],"geometry":"FAEED661-6D77-4353-AC8A-864483404956","material":"AB5A0168-698E-49CB-B5EB-71198AEBF417"}},"__threeObj":{"metadata":{"version":4.5,"type":"Object","generator":"Object3D.toJSON"},"geometries":[{"uuid":"FAEED661-6D77-4353-AC8A-864483404956","type":"SphereGeometry","radius":5,"widthSegments":6,"heightSegments":4,"phiStart":0}],"materials":[{"uuid":"AB5A0168-698E-49CB-B5EB-71198AEBF417","type":"MeshBasicMaterial","color":16766720,"depthFunc":3,"depthTest":true,"depthWrite":true,"stencilWrite":false,"stencilWriteMask":255,"stencilFunc":519,"stencilRef":0,"stencilFuncMask":255,"stencilFail":7680,"stencilZFail":7680,"stencilZPass":7680}],"object":{"uuid":"EC15B000-C0C7-4A30-91DB-F39857DC6F84","type":"Group","layers":1,"matrix":[1,0,0,0,0,1,0,0,0,0,1,0,755,724,-68,1],"children":[{"uuid":"46FDDBAD-5415-4310-A508-FEEEA70720AD","type":"Mesh","layers":1,"matrix":[1,0,0,0,0,1,0,0,0,0,1,0,0,0,0,1],"geometry":"FAEED661-6D77-4353-AC8A-864483404956","material":"AB5A0168-698E-49CB-B5EB-71198AEBF417"}]}},"index":22,"z":-68,"vx":0,"vy":0,"vz":0},{"id":"BFO:0000029","rdfs:label":"site","short_label":"site","rdfs:subClassOf":["BFO:0000141"],"parent_id":"BFO:0000141","children":[],"color":"#FFD700","depth":5,"radius":4,"fz":-58.4823617507989,"fx":537,"x":537,"fy":435,"y":435,"marker":{"metadata":{"version":4.5,"type":"Object","generator":"Object3D.toJSON"},"geometries":[{"uuid":"513E25E5-29F4-4DBA-B36D-86C6E285878D","type":"SphereGeometry","radius":5,"widthSegments":6,"heightSegments":4,"phiStart":0}],"materials":[{"uuid":"D833EE8E-1E9B-4F52-9E80-8F930886E2C5","type":"MeshBasicMaterial","color":16766720,"depthFunc":3,"depthTest":true,"depthWrite":true,"stencilWrite":false,"stencilWriteMask":255,"stencilFunc":519,"stencilRef":0,"stencilFuncMask":255,"stencilFail":7680,"stencilZFail":7680,"stencilZPass":7680}],"object":{"uuid":"7D628368-E95B-4059-9CC8-661FBF1D86A6","type":"Mesh","layers":1,"matrix":[1,0,0,0,0,1,0,0,0,0,1,0,0,0,0,1],"geometry":"513E25E5-29F4-4DBA-B36D-86C6E285878D","material":"D833EE8E-1E9B-4F52-9E80-8F930886E2C5"}},"__threeObj":{"metadata":{"version":4.5,"type":"Object","generator":"Object3D.toJSON"},"geometries":[{"uuid":"513E25E5-29F4-4DBA-B36D-86C6E285878D","type":"SphereGeometry","radius":5,"widthSegments":6,"heightSegments":4,"phiStart":0}],"materials":[{"uuid":"D833EE8E-1E9B-4F52-9E80-8F930886E2C5","type":"MeshBasicMaterial","color":16766720,"depthFunc":3,"depthTest":true,"depthWrite":true,"stencilWrite":false,"stencilWriteMask":255,"stencilFunc":519,"stencilRef":0,"stencilFuncMask":255,"stencilFail":7680,"stencilZFail":7680,"stencilZPass":7680}],"object":{"uuid":"15E7404D-6B1D-4867-99CB-B4875369694A","type":"Group","layers":1,"matrix":[1,0,0,0,0,1,0,0,0,0,1,0,537,435,-68,1],"children":[{"uuid":"7D628368-E95B-4059-9CC8-661FBF1D86A6","type":"Mesh","layers":1,"matrix":[1,0,0,0,0,1,0,0,0,0,1,0,0,0,0,1],"geometry":"513E25E5-29F4-4DBA-B36D-86C6E285878D","material":"D833EE8E-1E9B-4F52-9E80-8F930886E2C5"}]}},"index":23,"z":-68,"vx":0,"vy":0,"vz":0},{"id":"BFO:0000140","rdfs:label":"continuant fiat boundary","IAO:0000115":"b is a continuant fiat boundary = Def. b is an immaterial entity that is of zero, one or two dimensions and does not include a spatial region as part. (axiom label in BFO2 Reference: [029-001])","short_label":"continuant fiat boundary","rdfs:subClassOf":["BFO:0000141"],"parent_id":"BFO:0000141","children":["BFO:0000142","BFO:0000146","BFO:0000147"],"color":"#FFD700","depth":5,"radius":4,"fz":-58.25758772358553,"fx":833,"x":833,"fy":265,"y":265,"marker":{"metadata":{"version":4.5,"type":"Object","generator":"Object3D.toJSON"},"geometries":[{"uuid":"2E571A3E-0194-45AE-BD69-424EAB98F4B6","type":"SphereGeometry","radius":5,"widthSegments":6,"heightSegments":4,"phiStart":0}],"materials":[{"uuid":"948EE31F-F8D8-41F5-9D8D-4A44768D790A","type":"MeshBasicMaterial","color":16766720,"depthFunc":3,"depthTest":true,"depthWrite":true,"stencilWrite":false,"stencilWriteMask":255,"stencilFunc":519,"stencilRef":0,"stencilFuncMask":255,"stencilFail":7680,"stencilZFail":7680,"stencilZPass":7680}],"object":{"uuid":"8AB4080B-976D-45CD-B1DB-EF5E1FA1441C","type":"Mesh","layers":1,"matrix":[1,0,0,0,0,1,0,0,0,0,1,0,0,0,0,1],"geometry":"2E571A3E-0194-45AE-BD69-424EAB98F4B6","material":"948EE31F-F8D8-41F5-9D8D-4A44768D790A"}},"__threeObj":{"metadata":{"version":4.5,"type":"Object","generator":"Object3D.toJSON"},"geometries":[{"uuid":"2E571A3E-0194-45AE-BD69-424EAB98F4B6","type":"SphereGeometry","radius":5,"widthSegments":6,"heightSegments":4,"phiStart":0}],"materials":[{"uuid":"948EE31F-F8D8-41F5-9D8D-4A44768D790A","type":"MeshBasicMaterial","color":16766720,"depthFunc":3,"depthTest":true,"depthWrite":true,"stencilWrite":false,"stencilWriteMask":255,"stencilFunc":519,"stencilRef":0,"stencilFuncMask":255,"stencilFail":7680,"stencilZFail":7680,"stencilZPass":7680}],"object":{"uuid":"051EC1C8-A2F6-4674-8953-D838BBDB9B91","type":"Group","layers":1,"matrix":[1,0,0,0,0,1,0,0,0,0,1,0,833,265,-68,1],"children":[{"uuid":"8AB4080B-976D-45CD-B1DB-EF5E1FA1441C","type":"Mesh","layers":1,"matrix":[1,0,0,0,0,1,0,0,0,0,1,0,0,0,0,1],"geometry":"2E571A3E-0194-45AE-BD69-424EAB98F4B6","material":"948EE31F-F8D8-41F5-9D8D-4A44768D790A"}]}},"index":24,"z":-68,"vx":0,"vy":0,"vz":0},{"id":"BFO:0000016","rdfs:label":"disposition","short_label":"disposition","rdfs:subClassOf":["BFO:0000017"],"parent_id":"BFO:0000017","children":["BFO:0000034"],"color":"#FFD700","depth":5,"radius":4,"fz":-73.43735207035147,"fx":177,"x":177,"fy":-1402,"y":-1402,"marker":{"metadata":{"version":4.5,"type":"Object","generator":"Object3D.toJSON"},"geometries":[{"uuid":"E23E9620-10DA-4607-8BCA-A82141135386","type":"SphereGeometry","radius":5,"widthSegments":6,"heightSegments":4,"phiStart":0}],"materials":[{"uuid":"3CA9B2EA-7AEB-4E4F-B6CE-F9FEC9E603D4","type":"MeshBasicMaterial","color":16766720,"depthFunc":3,"depthTest":true,"depthWrite":true,"stencilWrite":false,"stencilWriteMask":255,"stencilFunc":519,"stencilRef":0,"stencilFuncMask":255,"stencilFail":7680,"stencilZFail":7680,"stencilZPass":7680}],"object":{"uuid":"4D891F8C-F7F7-45A4-B23A-3B31B0D8BFCD","type":"Mesh","layers":1,"matrix":[1,0,0,0,0,1,0,0,0,0,1,0,0,0,0,1],"geometry":"E23E9620-10DA-4607-8BCA-A82141135386","material":"3CA9B2EA-7AEB-4E4F-B6CE-F9FEC9E603D4"}},"__threeObj":{"metadata":{"version":4.5,"type":"Object","generator":"Object3D.toJSON"},"geometries":[{"uuid":"E23E9620-10DA-4607-8BCA-A82141135386","type":"SphereGeometry","radius":5,"widthSegments":6,"heightSegments":4,"phiStart":0}],"materials":[{"uuid":"3CA9B2EA-7AEB-4E4F-B6CE-F9FEC9E603D4","type":"MeshBasicMaterial","color":16766720,"depthFunc":3,"depthTest":true,"depthWrite":true,"stencilWrite":false,"stencilWriteMask":255,"stencilFunc":519,"stencilRef":0,"stencilFuncMask":255,"stencilFail":7680,"stencilZFail":7680,"stencilZPass":7680}],"object":{"uuid":"3287832B-8C36-4FB4-829B-157ECBC1D22F","type":"Group","layers":1,"matrix":[1,0,0,0,0,1,0,0,0,0,1,0,177,-1402,-68,1],"children":[{"uuid":"4D891F8C-F7F7-45A4-B23A-3B31B0D8BFCD","type":"Mesh","layers":1,"matrix":[1,0,0,0,0,1,0,0,0,0,1,0,0,0,0,1],"geometry":"E23E9620-10DA-4607-8BCA-A82141135386","material":"3CA9B2EA-7AEB-4E4F-B6CE-F9FEC9E603D4"}]}},"index":25,"z":-68,"vx":0,"vy":0,"vz":0},{"id":"BFO:0000023","rdfs:label":"role","short_label":"role","rdfs:subClassOf":["BFO:0000017"],"parent_id":"BFO:0000017","children":[],"color":"#FFD700","depth":5,"radius":4,"fz":-65.90625009592497,"fx":166,"x":166,"fy":-1238,"y":-1238,"marker":{"metadata":{"version":4.5,"type":"Object","generator":"Object3D.toJSON"},"geometries":[{"uuid":"58878677-28D1-4DFA-84E3-5E6FEE9046E2","type":"SphereGeometry","radius":5,"widthSegments":6,"heightSegments":4,"phiStart":0}],"materials":[{"uuid":"341DA4A7-49DA-4E06-8D62-14869BC1014D","type":"MeshBasicMaterial","color":16766720,"depthFunc":3,"depthTest":true,"depthWrite":true,"stencilWrite":false,"stencilWriteMask":255,"stencilFunc":519,"stencilRef":0,"stencilFuncMask":255,"stencilFail":7680,"stencilZFail":7680,"stencilZPass":7680}],"object":{"uuid":"1321C842-C162-4E6E-B94D-DEB0DCA75930","type":"Mesh","layers":1,"matrix":[1,0,0,0,0,1,0,0,0,0,1,0,0,0,0,1],"geometry":"58878677-28D1-4DFA-84E3-5E6FEE9046E2","material":"341DA4A7-49DA-4E06-8D62-14869BC1014D"}},"__threeObj":{"metadata":{"version":4.5,"type":"Object","generator":"Object3D.toJSON"},"geometries":[{"uuid":"58878677-28D1-4DFA-84E3-5E6FEE9046E2","type":"SphereGeometry","radius":5,"widthSegments":6,"heightSegments":4,"phiStart":0}],"materials":[{"uuid":"341DA4A7-49DA-4E06-8D62-14869BC1014D","type":"MeshBasicMaterial","color":16766720,"depthFunc":3,"depthTest":true,"depthWrite":true,"stencilWrite":false,"stencilWriteMask":255,"stencilFunc":519,"stencilRef":0,"stencilFuncMask":255,"stencilFail":7680,"stencilZFail":7680,"stencilZPass":7680}],"object":{"uuid":"25B25BBD-3F68-4155-94F4-FAC21C25DB19","type":"Group","layers":1,"matrix":[1,0,0,0,0,1,0,0,0,0,1,0,166,-1238,-68,1],"children":[{"uuid":"1321C842-C162-4E6E-B94D-DEB0DCA75930","type":"Mesh","layers":1,"matrix":[1,0,0,0,0,1,0,0,0,0,1,0,0,0,0,1],"geometry":"58878677-28D1-4DFA-84E3-5E6FEE9046E2","material":"341DA4A7-49DA-4E06-8D62-14869BC1014D"}]}},"index":26,"z":-68,"vx":0,"vy":0,"vz":0},{"id":"BFO:0000145","rdfs:label":"relational quality","IAO:0000115":"b is a relational quality = Def. for some independent continuants c, d and for some time t: b quality_of c at t & b quality_of d at t. (axiom label in BFO2 Reference: [057-001])","short_label":"relational quality","rdfs:subClassOf":["BFO:0000019"],"parent_id":"BFO:0000019","children":[],"color":"#FFD700","depth":5,"radius":4,"fz":-58.051876604684935,"fx":373,"x":373,"fy":-900,"y":-900,"marker":{"metadata":{"version":4.5,"type":"Object","generator":"Object3D.toJSON"},"geometries":[{"uuid":"0A062F1D-6359-4FB3-87CC-25CACD2D7A18","type":"SphereGeometry","radius":5,"widthSegments":6,"heightSegments":4,"phiStart":0}],"materials":[{"uuid":"DC470417-E091-4988-A58D-B06DA87F8B31","type":"MeshBasicMaterial","color":16766720,"depthFunc":3,"depthTest":true,"depthWrite":true,"stencilWrite":false,"stencilWriteMask":255,"stencilFunc":519,"stencilRef":0,"stencilFuncMask":255,"stencilFail":7680,"stencilZFail":7680,"stencilZPass":7680}],"object":{"uuid":"9BA1F191-065C-49A3-9D8A-295D270BC96A","type":"Mesh","layers":1,"matrix":[1,0,0,0,0,1,0,0,0,0,1,0,0,0,0,1],"geometry":"0A062F1D-6359-4FB3-87CC-25CACD2D7A18","material":"DC470417-E091-4988-A58D-B06DA87F8B31"}},"__threeObj":{"metadata":{"version":4.5,"type":"Object","generator":"Object3D.toJSON"},"geometries":[{"uuid":"0A062F1D-6359-4FB3-87CC-25CACD2D7A18","type":"SphereGeometry","radius":5,"widthSegments":6,"heightSegments":4,"phiStart":0}],"materials":[{"uuid":"DC470417-E091-4988-A58D-B06DA87F8B31","type":"MeshBasicMaterial","color":16766720,"depthFunc":3,"depthTest":true,"depthWrite":true,"stencilWrite":false,"stencilWriteMask":255,"stencilFunc":519,"stencilRef":0,"stencilFuncMask":255,"stencilFail":7680,"stencilZFail":7680,"stencilZPass":7680}],"object":{"uuid":"75A62F38-AC50-4345-B36E-6804BA0E1C1C","type":"Group","layers":1,"matrix":[1,0,0,0,0,1,0,0,0,0,1,0,373,-900,-68,1],"children":[{"uuid":"9BA1F191-065C-49A3-9D8A-295D270BC96A","type":"Mesh","layers":1,"matrix":[1,0,0,0,0,1,0,0,0,0,1,0,0,0,0,1],"geometry":"0A062F1D-6359-4FB3-87CC-25CACD2D7A18","material":"DC470417-E091-4988-A58D-B06DA87F8B31"}]}},"index":27,"z":-68,"vx":0,"vy":0,"vz":0}]